Workbook

Sheet Id
B1: Preencher o nome e RA na Planilha Id, células C9 e C10 | E1: Valor | F1: ='Q1'!H1+'Q2'!G1+'Q3'!G1+'Q4'!H1+'Q5'!E1 -> 10.5
B3: Fatec Zona Sul
B4: Atividade P2 - 2S2025
B5: Gestão de Projetos
B6: Prof. Carlos Giordano
B7: giordanofatec@yahoo.com.br
B9: Nome: | C9: Felipe de Jesus dos Reis
B10: RA: | C10: 1370482421013
B12: 1. Após responder, enviar para giordanofatec@yahoo.com.br.
B13: 2. Assunto do e-mail a enviar: P2 Seunome 2S2025
B14: 3. Aguardar a confirmação do recebimento.
B17: Atenção: Valor da atividade: 10,5. Nota máxima 10,0, sem saldo para as atividades posteriores.
B18: Atenção: A atividade P2 é um Projeto com data e hora de entrega. Atrasos geram descontos referentes às multas pertinentes.

Sheet Q1
B1: =Id!B1 -> Preencher o nome e RA na Planilha Id, células C9 e C10 | G1: Valor | H1: 0.75
B3: Se existirem, assinalar a(s) alternativa(s) correta(s) sobre o framework Scrum:
B5: ( ) O Manifesto ágil valoriza mais os acertos financeiros do que o bom relacionamento com o cliente. | G5: O Manifesto Ágil valoriza colaboração com o cliente mais que negociação de contratos
B6: ( ) O Incremento do Produto faz parte do Backlog. | G6: O incremento é o resultado do Sprint, não um item do backlog
B7: ( ) O Daily Scrum se refere às discussões sobre as lições aprendidas, aplicáveis aos próximos Sprints. | G7: Isso ocorre na Sprint Retrospective, o Daily Scrum é uma reunião diária de 15 min para inspecionar progresso
B8: ( ) É aplicável somente a projetos de software de qualquer duração. | G8: Scrum pode ser aplicado em qualquer domínio, não apenas software
B9: ( ) O Backlog do Produto é um outro nome dado ao Backlog da Sprint. | G9: Product Backlog: lista de tudo que o produto precisa e Sprint Backlog: itens selecionados para a Sprint + plano para entregá-los
B10: ( ) Uma das vantagens do Scrum é o foco total no time de Projetos. | G10: O foco é no valor entregue ao cliente, não apenas no time
B11: ( ) Os papeis centrais incluem: Dono do Produto, Scrum Master e Cliente. | G11: Os papéis são: Product Owner, Scrum Master e Developers. “Cliente” não é um papel do Scrum
B12: ( ) O Scrum Master entrega valor de negócio ao cliente. | G12: Quem maximiza o valor é o Product Owner. O Scrum Master facilita o processo.
B14: Selecionar uma alternativa não assinalada como correta, escrever o correto e explicar o porquê.

Sheet Q2
B1: =Id!B1 -> Preencher o nome e RA na Planilha Id, células C9 e C10 | F1: Valor | G1: 0.75
B3: Dos itens a seguir, assinalar qual(is) não faz(em) parte do método Kanban:
B5: ( x ) Cálculo e reserva do valor de contingência para proteção aos riscos. | F5: Isso é prática de gestão de riscos tradicional/preditiva, não do Kanban
B6: ( x ) O sistema funciona por meio de atividades e tarefas empurradas. | F6: Kanban trabalha com sistema puxado (pull system), não empurrado
B7: ( x ) Revisão por meio das StandUp. | F7: Stand-up meetings são uma prática comum, mas não fazem parte do método Kanban em sua essência; o método não define cerimônias obrigatórias
B8: ( x ) Finalização do Time-boxed. | F8: Kanban não usa time-box, essa é uma característica do Scrum
B9: ( x ) Não se adapta ao framework Scrum. | F9: Kanban pode ser integrado ao Scrum
B10: ( x ) Aplicativo MS Project. | F10: É apenas uma ferramenta de planejamento tradicional, não parte do método
B11: ( ) Uso de cartões coloridos para efeito de atenção.
B12: ( ) Reuniões de fluxo.
B14: Selecionar uma alternativa assinalada e explicar o porquê da assinalação.

Sheet Q3
B1: =Id!B1 -> Preencher o nome e RA na Planilha Id, células C9 e C10 | F1: Valor | G1: 2
B3: Pede-se:
B4: a) Avaliar as quatro situações (S1 a S4) do Quadro, relativas às situações dos Projetos P1 a P4, diferentes, mediante elaboração dos cálculos necessários.
B5: b) Determinar as situações dos quatro projetos, em termos de prazo e custo (provar com pelo menos um cálculo).
B6: c) Calcular, em reais, as estimativas de quanto os quatro projetos gastarão a mais ou economizarão ao final, para as quatro situações. Calcular e informar todos os valores apurados.
B7: d) Qual dos projetos corre o maior Risco de alterações no cronograma e no custo? Por quê? | C7: A) | G7: S1 | H7: S2 | I7: S3 | J7: S4
F8: VP | G8: 110 | H8: 130 | I8: 150 | J8: 120
B9: Informação: valor do ONT de todas as situações: 12.350. | F9: VA | G9: 100 | H9: 130 | I9: 100 | J9: 150
F10: CR | G10: 100 | H10: 120 | I10: 120 | J10: 130
F11: ONT | G11: 12350 | H11: 12350 | I11: 12350 | J11: 12350
F12: VC | G12: =G9-G10 -> 0 | H12: =H9-H10 -> 10 | I12: =I9-I10 -> -20 | J12: =J9-J10 -> 20
F13: IDC | G13: =G9/G10 -> 1 | H13: =H9/H10 -> 1.0833333 | I13: =I9/I10 -> 0.83333333 | J13: =J9/J10 -> 1.1538462
F14: VPR | G14: =G9-G8 -> -10 | H14: =H9-H8 -> 0 | I14: =I9-I8 -> -50 | J14: =J9-J8 -> 30
F15: IDP | G15: =G9/G8 -> 0.90909091 | H15: =H9/H8 -> 1 | I15: =I9/I8 -> 0.66666667 | J15: =J9/J8 -> 1.25
F16: ENT | G16: =G11/G13 -> 12350 | H16: =H11/H13 -> 11400 | I16: =I11/I13 -> 14820 | J16: =J11/J13 -> 10703.333
F17: EPT | G17: =G16-G10 -> 12250 | H17: =H16-H10 -> 11280 | I17: =I16-I10 -> 14700 | J17: =J16-J10 -> 10573.333
F18: VCN | G18: =G11-G16 -> 0 | H18: =H11-H16 -> 950 | I18: =I11-I16 -> -2470 | J18: =J11-J16 -> 1646.6667
C20: B) | F20: S1: VPR = −10, logo atrasado; VC = 0, logo está no custo
F21: S2: VPR = 0, logo está no prazo; VC = 10, logo econômico (sobrou custo).
F22: S3: VPR = −50, logo está atrasado; VC = −20, logo estourou o custo
F23: S4: VPR = 30, logo está adiantado; VC = 20, logo é econômico (sobrou custo).
C25: C) | F25: S1: VCN = 0, nenhuma variação.
F26: S2: VCN = 950, economia de R$ 950,00
F27: S3: VCN = -2.470, previsão de gastar R$2.470,00 a mais (estouro).
F28: S4: VCN = 1.646,67, economia de R$1.646,67
C30: D) | F30: S3 é o que corre maior risco de mudanças / problemas, porque:
F31: Índices de desempenho ambos < 1: IDC = 0,833 (<1) indica tendência de gasto acima do previsto (pior custo); IDP = 0,667 (<1) indica forte atraso relativo ao plano.
F32: Variância ao término negativa: VCN = −2.470, ou seja a EAC é bem maior que o orçamento (previsão de sobrecusto).
F33: VPR = −50 mostra um atraso significativo no cronograma.
F34: Portanto S3 apresenta tanto risco de atraso quanto de estouro de custo.

Sheet Q4
G1: Valor | H1: 3 | N1: =[1]Id!B1 -> Preencher o nome e RA na Planilha Id, células C9 e C10
B3: 0 | C3: ="1-"&D6 -> 1-3 | D3: =B3+D6 -> 3 | F3: =D3 -> 3 | G3: =F3+1&"-"&H3 -> 4-5,5 | H3: =F3+H6 -> 5.5 | J3: =H3 -> 5.5 | K3: =J3+1&"-"&L3 -> 6,5-7 | L3: =J3+L6 -> 7 | O3: Tabela | V3: Recurso | W3: Competente Tarefa | X3: Entrega em/horas | Y3: Custo RH | Z3: Base | AB3: Custo/Hora
B4: T1 | F4: T3 | J4: T5 | O4: Tarefa | P4: RH Alocado | Q4: Custo RH/h | R4: Horas Alocadas | S4: Custo da Tarefa | V4: Lisa | W4: 2 | X4: 1.5 | Y4: 50 | Z4: Hora | AB4: 50
O5: 1 | P5: =V7 -> Marge | Q5: =AB7 -> 17.5 | R5: =X7 -> 3 | S5: =Q5*R5 -> 52.5 | V5: Homer | W5: 2 | X5: 3.5 | Y5: 160 | Z5: Dia | AB5: =Y5/8 -> 20
B6: 1 | C6: =P5 -> Marge | D6: =R5 -> 3 | F6: 3 | G6: =P7 -> Bart | H6: =R7 -> 2.5 | J6: 5 | K6: =P9 -> Lovejoy | L6: =R9 -> 1.5 | O6: 2 | P6: =V5 -> Homer | Q6: =AB5 -> 20 | R6: =X5 -> 3.5 | S6: =Q6*R6 -> 70 | W6: 3 | X6: 4
O7: 3 | P7: =V16 -> Bart | Q7: =AB16 -> 16.666667 | R7: =X16 -> 2.5 | S7: =Q7*R7 -> 41.666667 | V7: Marge | W7: 1 | X7: 3 | Y7: 140 | Z7: Dia | AB7: =Y7/8 -> 17.5
B8: 0 | C8: ="1-"&D11 -> 1-3,5 | D8: =B8+D11 -> 3.5 | F8: =D8 -> 3.5 | G8: =F8+1&"-"&H8 -> 4,5-8,5 | H8: =F8+H11 -> 8.5 | J8: =H8 -> 8.5 | K8: =J8+1&"-"&L8 -> 9,5-10,5 | L8: =J8+L11 -> 10.5 | O8: 4 | P8: =V7 -> Marge | Q8: =AB7 -> 17.5 | R8: =X8 -> 5 | S8: =Q8*R8 -> 87.5 | W8: 4 | X8: 5
B9: T2 | F9: T4 | J9: T6 | O9: 5 | P9: =V13 -> Lovejoy | Q9: =AB13 -> 45 | R9: =X13 -> 1.5 | S9: =Q9*R9 -> 67.5 | V9: Maggie | W9: 1 | X9: 2 | Y9: 28 | Z9: Hora | AB9: 28
O10: 6 | P10: =V15 -> Backy | Q10: =AB15 -> 20.833333 | R10: =X15 -> 2 | S10: =Q10*R10 -> 41.666667 | W10: 3 | X10: 1.5
B11: 2 | C11: =P6 -> Homer | D11: =R6 -> 3.5 | F11: 4 | G11: =P8 -> Marge | H11: =R8 -> 5 | J11: 6 | K11: =P10 -> Backy | L11: =R10 -> 2 | O11: Total | S11: =SUM(S5:S10) -> 360.83333 | V11: Laura | W11: 1 | X11: 1 | Y11: 4200 | Z11: Semana | AB11: =Y11/7/8 -> 75
W12: 4 | X12: 3.5
V13: Lovejoy | W13: 5 | X13: 1.5 | Y13: 360 | Z13: Dia | AB13: =Y13/8 -> 45
W14: 6 | X14: 1
V15: Backy | W15: 6 | X15: 2 | Y15: 2500 | Z15: Quinzena | AB15: =Y15/15/8 -> 20.833333
V16: Bart | W16: 3 | X16: 2.5 | Y16: 4000 | Z16: Mês | AB16: =Y16/30/8 -> 16.666667
W17: 4 | X17: 5.5
V18: Matt | W18: 1 | X18: 1.5 | Y18: 45 | Z18: Hora | AB18: =Y18 -> 45
B19: - Observar o Diagrama de Rede composto por 6 Tarefas, | W19: 5 | X19: 2
B20: atentando para as precedências e durações em dias corridos. | W20: 6 | X20: 2.5
B21: - Observar o Quadro mostrando os recursos disponíveis, as
B22: tarefas em que os recursos são competentes, a entrega em | AB22: Custo RH | AC22: Resultado
B23: horas e o custo informado pelo RH. | O23: Tarefas do Caminho Crítico: | R23: 2;4;6 | S23: 3 | AB23: Dia/8 | AC23: Hora
O24: Tarefas com Folga (horas de Folga): | R24: 1(0,5*);3(5*);5(3,5*) | S24: 3 | T24: obs: a tarefa 1 tem essa folga, porque o Recurso está alocado na tarefa 4 também | AB24: Semana/7 | AC24: Dia
B25: Pede-se: | O25: % Tarefas do caminho crítico: | R25: =S23/6 -> 0.5 | AB25: Quinzena/15 | AC25: Dia
B26: 1. Alocar os recursos nas Tarefas visando ao final | AB26: Mês/30 | AC26: Dia
B27: o menor custo. Alocar um recurso por Tarefa. | O27: número de horas totais do Projeto: | R27: =L8 -> 10.5 | S27: =AB12&" horas" -> horas
B28: 2. Informar o total de dias corridos do projeto.
B29: 3. Criar Tabela em que se detalham a alocação do | O29: quantidade de dias do Projeto: | R29: =L8/8 -> 1.3125 | S29: dia
B30: recurso e o custo de cada Tarefa.
B31: 4. Apresentar na Tabela criada o custo Total. | O31: Custo do projeto: | R31: =S11 -> 360.83333
B32: 5. Informar as tarefas do caminho crítico e com folga.

Sheet Q5
B1: =Id!B1 -> Preencher o nome e RA na Planilha Id, células C9 e C10 | D1: Valor | E1: 4
B3: Em um Projeto de desenvolvimento de normas de segurança existem os seguintes Riscos: | F3: Fase 1 | K3: Fase 2 | L3: Fase 3
D4: Tarefa | E4: Risco | F4: +/- | G4: P1% | H4: I1R$ | I4: Custo Tarefa | J4: I1% | K4: Estratégia | L4: P2% | M4: I2R$ | N4: Reserva R$ | O4: Efeito no Projeto
B5: 1) T39 - Modificações no escopo por parte da alta administração (Impacto 1: 13% de R$25.500); | D5: 39 | E5: Modificações no escopo (alta administração) | F5: - | G5: 0.4 | H5: =I5*J5 -> 3315 | I5: 25500 | J5: 0.13 | K5: Eliminar | L5: 0.05 | M5: 663 | N5: =L5*M5 -> 33.15 | O5: Redução quase total do risco
B6: 2) T41 - Treinamentos antecipados (impacto 1: 23% de R$11.000) | D6: 41 | E6: Treinamentos antecipados | F6: + | G6: 0.2 | H6: =I6*J6 -> 2530 | I6: 11000 | J6: 0.23 | K6: Explorar | L6: 0.5 | M6: 3036 | N6: =-L6*M6 -> -1518 | O6: Ganho esperado no cronograma
B7: 3) T64 – Alterações nos critérios de Qualidade (impacto 1: 27% de R$40.000,00). | D7: 64 | E7: Alterações nos critérios de Qualidade | F7: - | G7: 0.3 | H7: =I7*J7 -> 10800 | I7: 40000 | J7: 0.27 | K7: Transferir | L7: 0.1 | M7: 1080 | N7: =L7*M7 -> 108 | O7: Redução do impacto via contrato
B8: 4) T88 - Falhas nos equipamentos de Tecnologia da Informação (impacto 1: 31% de R$28.500); e, | D8: 88 | E8: Falhas nos equipamentos de TI | F8: - | G8: 0.25 | H8: =I8*J8 -> 8835 | I8: 28500 | J8: 0.31 | K8: Mitigar | L8: 0.1 | M8: 4417.5 | N8: =L8*M8 -> 441.75 | O8: Redução de falhas via manutenção/SLA
B9: 5) T94 – Valor do Euro (impacto 1: 53% de R$23.100). | D9: 94 | E9: Variação do valor do Euro | F9: - | G9: 0.35 | H9: =I9*J9 -> 12243 | I9: 23100 | J9: 0.53 | K9: Aceitar | L9: 0.35 | M9: =H9 -> 12243 | N9: =L9*M9 -> 4285.05 | O9: Exposição mantida ao câmbio
D10: Contingência (reserva) | O10: =SUM(N5:N9) -> 3349.95
B11: Pede-se, arbitrar e responder justificando detalhadamente (em cada uma das cinco tarefas): | D11: Riscos positivos | O11: =N6 -> -1518
B12: a) Fase 1: arbitrar o tipo do risco (+ ou -), a Probabilidade 1 e calcular o Valor de Contingência 1 previsto para cada risco.
B13: b) Fase 2: para cada risco, escolher qual a melhor Estratégia a ser adotada (não repetir estratégias). | C13: E) | D13: Criar reserva financeira realista para riscos identificados.
B14: c) Fase 3: depois das estratégias adotadas, qual a Probabilidade 2 e o Impacto 2 em R$ planejados de cada risco. | D14: Proteger cronograma e orçamento contra eventos adversos.
B15: d) Qual o total de contingência em reais reservado ou economizado pelo projeto. | D15: Tomar decisões racionais: comparar custo de resposta versus custo esperado do risco.
D16: Mostrar transparência aos stakeholders (justificar orçamento acima do custo-base).
B17: e) Responder detalhadamente: Afinal, para que serve o valor de contingência calculado? | D17: Medir eficácia das respostas (comparando Contingência 1 e Contingência 2).
D18: Diferenciar riscos negativos e oportunidades, incluindo ganhos planejados.
B19: Lembrando: | D19: Evitar surpresas: quando um risco ocorre, os recursos já estão previstos.
B20: Nos exercícios em sala e nas Ps alguns valores são arbitrados, no mundo real esses valores devem ser APURADOS.
