Workbook

Sheet Id
B1: Preencher o nome e RA na Planilha Id, células C9 e C10 | G1: Valor | H1: ='Q1'!H1+'Q2'!H1+'Q3'!L1+'Q5'!H1+'Q4'!$H$1 -> 10.5
B3: Fatec Zona Sul
B4: Atividade P1 - 2S2025
B5: Gestão de Projetos
B6: Prof. Carlos Giordano
B7: giordanofatec@yahoo.com.br
B9: Nome: | C9: Felipe de Jesus dos Reis
B10: RA: | C10: 1370482421013
B12: 1. Após responder, enviar para giordanofatec@yahoo.com.br.
B13: 2. Assunto do e-mail a enviar: P1 Seunome 2S2025.
B14: 3. Aguardar a confirmação do recebimento.
B17: Atenção: Valor da atividade: 10,5. Nota máxima 10,0, sem saldo para as atividades posteriores.
B18: Atenção: A atividade P1 é um Projeto com data e hora de entrega. Atrasos geram descontos referentes às multas pertinentes.
C20: Data e hora da entrega: até 03/10/2025, às 10h30

Sheet Q1
B1: =Id!B1 -> Preencher o nome e RA na Planilha Id, células C9 e C10 | G1: Valor | H1: 1.5
B3: I. Assinalar as afirmações abaixo, grafando F para Falso ou V para Verdadeiro:
B5: V | C5: A alocação de recursos é feita pela equipe durante os sprints, sem fases tradicionais.
B6: F | C6: No caso da New Millenium, após a verificação da não inclusão de Atividades ao Projeto, quando a Leslie diz ao Alex que “mesmo assim espero que você se atenha ao mesmo prazo final e às restrições orçamentárias”, esse pedido pode ser atendido prontamente.
B7: F | C7: *O caminho crítico é calculado para identificar tarefas com folga, priorizando-as no cronograma.
B8: V | C8: Deve-se elaborar simulações a fim de alocar o recurso adequado à tarefa, observando o custo do recurso e o tempo que o recurso completará a tarefa.
B9: F | C9: *A duração total do projeto se calcula somando as durações das tarefas do caminho crítico e as durações das tarefas com folga.
B10: V | C10: O Gerente de Projetos para melhor distribuir os recursos humanos nos projetos deve combinar os recursos das tarefas com folga para utilizá-los nas tarefas do caminho crítico.
B11: V | C11: Dependendo da necessidade, Tarefas com Folga podem se tornar Tarefas do Caminho Crítico.
B12: V | C12: Se há tarefas em paralelo deve-se ter atenção especial na alocação dos recursos, evitando superalocações.
B13: F | C13: O calendário dos recursos é integrado ao Quadro Kanban para otimizar tarefas em paralelo.
B14: V | C14: Os requisitos são coletados e validados no processo de iniciação influenciando diretamente a alocação de recursos humanos e materiais.

Sheet Q2
B1: =Id!B1 -> Preencher o nome e RA na Planilha Id, células C9 e C10 | G1: Valor | H1: 2
B3: Se existirem, selecionar DUAS das respostas assinaladas como F na Q1, corrigi-las e explicar detalhadamente o porquê da assinalação como Falsa.
B5: Resposta 1: | C5: O caminho crítico mostra atividades sem folga e que determinam a duração do projeto. As com folga não são priorizadas, são as sem folga.
B16: Resposta 2: | C16: A duração total do projeto é determinada somente pelas tarefas do caminho crítico.

Sheet Q3
A1: =Id!B1 -> Preencher o nome e RA na Planilha Id, células C9 e C10 | K1: Valor | L1: =SUM(AF13:AF19) -> 4
B3: 0 | C3: =B3+1&"-"&D3 -> 1-5 | D3: =B3+D6 -> 5 | F3: =D3 -> 5 | G3: =F3+1&"-"&H3 -> 6-6 | H3: =F3+H6 -> 6 | J3: =H13 -> 10 | K3: =J3+1&"-"&L3 -> 11-11 | L3: =J3+L6 -> 11 | N3: =L3 -> 11 | O3: =N3+1&"-"&P3 -> 12-14 | P3: =N3+P6 -> 14 | R3: =P8 -> 15 | S3: =R3+1&"-"&T3 -> 16-16,5 | T3: =R3+T6 -> 16.5 | V3: Detalhamento:
B4: A | F4: B | J4: F | N4: G | R4: I | V4: O primeiro Quadro se refere ao Projeto Venda App da empresa Qrovender Ltda (duração em dias).
V5: O segundo Quadro mostra os Custos dos Recursos.
B6: 1 | C6: =V27 -> Version | D6: 5 | F6: 2 | G6: =V37 -> UserId | H6: 1 | J6: 6 | K6: =V35 -> Order | L6: 1 | N6: 7 | O6: =V28 -> Parse | P6: 3 | R6: 9 | S6: =V26 -> Select | T6: 1.5 | V6: Quando mensal, para calcular o custo dia, dividir por 30.
V7: Quando quinzenal, para calcular o custo dia, dividir por 15.
F8: =D3 -> 5 | G8: =F8+1&"-"&H8 -> 6-8 | H8: =F8+H11 -> 8 | N8: =L3 -> 11 | O8: =N8+1&"-"&P8 -> 12-15 | P8: =N8+P11 -> 15 | V8: Quando semanal, para calcular o custo dia, dividir por 7.
F9: C | N9: H | V9: A empresa trabalha 8 horas por dia, não trabalha aos sábados, domingos e feriados.
V10: A empresa não emenda feriados.
F11: 3 | G11: =V33 -> Where | H11: 3 | N11: 8 | O11: =V31 -> Choose | P11: 4
V12: Pede-se:
F13: =D3 -> 5 | G13: =F13+1&"-"&H13 -> 6-10 | H13: =F13+H16 -> 10 | V13: a) | W13: O Diagrama de Rede do Projeto. | AF13: 1
F14: D | V14: b) | W14: A duração do Projeto em dias seguidos, sem calendário. | AF14: 0.5
V15: c) | W15: A data e o período do dia do início do Projeto, tendo como data da entrega 28/11/2025,
F16: 4 | G16: =V28 -> Parse | H16: 5 | W16: ao meio dia (ver calendário). | AF16: 0.5
V17: d) | W17: Identificação e porcentagem das Tarefas do Caminho Crítico e das Tarefas com Folga. | AF17: 0.5
F18: =D3 -> 5 | G18: =F18+1&"-"&H18 -> 6-9 | H18: =F18+H21 -> 9 | V18: e) | W18: Identificar a quantidade de dias de folga em cada Tarefa com Folga. | AF18: 0.5
F19: E | V19: f) | W19: O Custo do Projeto, utilizando só um Recurso em cada Tarefa. | AF19: 1
F21: 5 | G21: =V31 -> Choose | H21: 4 | W21: Materiais para elaboração fornecidos (setas, retas etc.)
W22: Obs.: elaborar na planilha todos os cálculos pertinentes.
V25: RECURSO | W25: CUSTO/HORA | AA25: Tarefas do Caminho Crítico: | AE25: 1;4;6;8;9 | AF25: 5
V26: Select | W26: =640/8 -> 80 | AA26: Tarefas com Folga (dias com Folga): | AE26: 2(4*);3(2*);5(*1);7(1) | AF26: 4
V27: Version | W27: =75 -> 75 | AA27: % Tarefas do caminho crítico: | AE27: =AF25/(AF25+AF26) -> 0.55555556
V28: Parse | W28: =40 -> 40
V29: Cursor | W29: =12000/15/8 -> 100 | AA29: A duração do Projeto em dias seguidos: | AE29: 16,5 dias
V30: Datetime | W30: =50 -> 50 | AA30: A data do início: | AE30: 45966
V31: Choose | W31: =8400/30/8 -> 35 | AE31: pela manhã as 08h00
V32: From | W32: =480/8 -> 60
V33: Where | W33: =30 -> 30 | AA33: Tabela
V34: Use | W34: =85 -> 85 | AA34: Tarefa | AB34: RH Alocado | AC34: Custo T RH | AD34: Outros Custos | AE34: Custo da Tarefa
V35: Order | W35: =6720/7/8 -> 120 | AA35: 1 | AB35: =C6 -> Version | AC35: =W27*D6*8 -> 3000 | AD35: 1000 | AE35: =AC35+AD35 -> 4000
V36: Dbld | W36: =100 -> 100 | AA36: 2 | AB36: =G6 -> UserId | AC36: =W37*H6*8 -> 200 | AD36: 0 | AE36: =AC36+AD36 -> 200
V37: UserId | W37: =200/8 -> 25 | AA37: 3 | AB37: =G11 -> Where | AC37: =W33*H11*8 -> 720 | AD37: 0 | AE37: =AC37+AD37 -> 720
AA38: 4 | AB38: =G16 -> Parse | AC38: =W28*H16*8 -> 1600 | AD38: 2500 | AE38: =AC38+AD38 -> 4100
AA39: 5 | AB39: =G21 -> Choose | AC39: =W31*H21*8 -> 1120 | AD39: 650 | AE39: =AC39+AD39 -> 1770
AA40: 6 | AB40: =K6 -> Order | AC40: =W35*L6*8 -> 960 | AD40: 1780 | AE40: =AC40+AD40 -> 2740
AA41: 7 | AB41: =O6 -> Parse | AC41: =W28*P6*8 -> 960 | AD41: 0 | AE41: =AC41+AD41 -> 960
AA42: 8 | AB42: =O11 -> Choose | AC42: =W31*P11*8 -> 1120 | AD42: 3000 | AE42: =AC42+AD42 -> 4120
AA43: 9 | AB43: =S6 -> Select | AC43: =W26*T6*8 -> 960 | AD43: 1500 | AE43: =AC43+AD43 -> 2460
AA44: Total | AE44: =SUM(AE35:AE43) -> 21070

Sheet Q4
G1: Valor | H1: 1.5 | N1: =Id!B1 -> Preencher o nome e RA na Planilha Id, células C9 e C10
B3: 0 | C3: =B3+1&"-"&D3 -> 1-1 | D3: =B3+D6 -> 1 | F3: =D3 -> 1 | G3: =F3+1&"-"&H3 -> 2-2,5 | H3: =F3+H6 -> 2.5 | J3: =H3 -> 2.5 | K3: =J3+1&"-"&L3 -> 3,5-5,5 | L3: =J3+L6 -> 5.5 | O3: Tabela | V3: Recurso | W3: Competente Tarefa | X3: Entrega em/horas | Y3: Custo RH | Z3: Base | AB3: Custo/Hora
B4: T1 | F4: T2 | J4: T4 | O4: Tarefa | P4: RH Alocado | Q4: Custo RH/h | R4: Horas Alocadas | S4: Custo da Tarefa | V4: Clarice | W4: 2 | X4: 1.5 | Y4: 42.35 | Z4: Hora | AB4: =Y4 -> 42.35
O5: 1 | P5: =V11 -> Rachel | Q5: =AB11 -> 74.196429 | R5: =X11 -> 1 | S5: =Q5*R5 -> 74.196429 | V5: Cecília | W5: 2 | X5: 3.5 | Y5: 180 | Z5: Dia | AB5: =Y5/8 -> 22.5
B6: 1 | C6: =P5 -> Rachel | D6: =R5 -> 1 | F6: 2 | G6: =P6 -> Clarice | H6: =R6 -> 1.5 | J6: 4 | K6: =P8 -> Rachel | L6: =R8 -> 3 | O6: 2 | P6: =V4 -> Clarice | Q6: =AB4 -> 42.35 | R6: =X4 -> 1.5 | S6: =Q6*R6 -> 63.525 | W6: 3 | X6: 2
O7: 3 | P7: =V9 -> Lygia | Q7: =AB9 -> 28.49 | R7: =X10 -> 1.5 | S7: =Q7*R7 -> 42.735 | V7: Djamila | W7: 1 | X7: 2.5 | Y7: 160 | Z7: Dia | AB7: =Y7/8 -> 20
F8: =D3 -> 1 | G8: =F8+1&"-"&H8 -> 2-2,5 | H8: =F8+H11 -> 2.5 | J8: =H3 -> 2.5 | K8: =J8+1&"-"&L8 -> 3,5-4 | L8: =J8+L11 -> 4 | O8: 4 | P8: =V11 -> Rachel | Q8: =AB11 -> 74.196429 | R8: =X12 -> 3 | S8: =Q8*R8 -> 222.58929 | W8: 4 | X8: 4.5
F9: T3 | J9: T5 | O9: 5 | P9: =V13 -> Carolina | Q9: =AB13 -> 43 | R9: =X13 -> 1.5 | S9: =Q9*R9 -> 64.5 | V9: Lygia | W9: 1 | X9: 2 | Y9: 28.49 | Z9: Hora | AB9: =Y9 -> 28.49
O10: 6 | P10: =V15 -> Hilda | Q10: =AB15 -> 25 | R10: =X15 -> 2.5 | S10: =Q10*R10 -> 62.5 | W10: 3 | X10: 1.5
F11: 3 | G11: =P7 -> Lygia | H11: =R7 -> 1.5 | J11: 5 | K11: =P9 -> Carolina | L11: =R9 -> 1.5 | O11: Total | S11: =SUM(S5:S10) -> 530.04571 | V11: Rachel | W11: 1 | X11: 1 | Y11: 4155 | Z11: Semana | AB11: =Y11/7/8 -> 74.196429
W12: 4 | X12: 3
J13: =H8 -> 2.5 | K13: =J13+1&"-"&L13 -> 3,5-5 | L13: =J13+L16 -> 5 | V13: Carolina | W13: 5 | X13: 1.5 | Y13: 344 | Z13: Dia | AB13: =Y13/8 -> 43
J14: T6 | W14: 6 | X14: 1
V15: Hilda | W15: 6 | X15: 2.5 | Y15: 3000 | Z15: Quinzena | AB15: =Y15/15/8 -> 25
J16: 6 | K16: =P10 -> Hilda | L16: =R10 -> 2.5 | V16: Firmina | W16: 3 | X16: 2.5 | Y16: 8900 | Z16: Mês | AB16: =Y16/30/8 -> 37.083333
W17: 4 | X17: 4
V18: Cora | W18: 1 | X18: 1.5 | Y18: 34.9 | Z18: Hora | AB18: =Y18 -> 34.9
B19: - Observar o Diagrama de Rede composto por 6 Tarefas, | W19: 5 | X19: 2
B20: atentando para as precedências e durações em horas corridas. | W20: 6 | X20: 2.5
B21: - Observar o Quadro mostrando os recursos disponíveis, as
B22: tarefas em que os recursos são competentes, a entrega em | AB22: Custo RH | AC22: Resultado
B23: horas e o custo informado pelo RH. | AB23: Dia/8 | AC23: Hora
AB24: Semana/7 | AC24: Dia
B25: Pede-se: | AB25: Quinzena/15 | AC25: Dia
B26: 1. Alocar os recursos nas Tarefas visando ao final | O26: Tarefas do Caminho Crítico: | S26: 1;2;3;4 | T26: 4 | AB26: Mês/30 | AC26: Dia
B27: a menor duração. Alocar um recurso por Tarefa. | O27: Tarefas com Folga horas com Folga): | S27: 5(*1,5);7(*0,5) | T27: 2
B28: 2. Informar o total de dias corridos do projeto. | O28: % Tarefas do caminho crítico: | S28: =T26/(T26+T27) -> 0.66666667
B29: 3. Criar Tabela em que se detalham a alocação do
B30: recurso e o custo de cada Tarefa. | O30: A duração do Projeto em dias seguidos: | S30: 1 dia
B31: 4. Apresentar na Tabela criada o custo Total. | O31: A data do fim: | S31: 45964
B32: 5. Iniciando o Projeto no dia 03/11/2025, pela manhã, | S32: pela tarde as 13h30
B33: em que dia e hora do dia será encerrado?
B34: 6. identificar as tarefas do caminho crítico e com folga.
B35: 7. Informar a porcentagem de Tarefas Críticas do
B36: Projeto e a criticidade do Projeto.

Sheet Q5
B1: =Id!B1 -> Preencher o nome e RA na Planilha Id, células C9 e C10 | G1: Valor | H1: 1.5
B3: Depois de elaborada a primeira versão (em Q3), o Patrocinador pede, até o possível | K3: 0 | L3: =K3+1&"-"&M3 -> 1-2,5 | M3: =K3+M6 -> 2.5 | O3: =M3 -> 2.5 | P3: =O3+1&"-"&Q3 -> 3,5-3,5 | Q3: =O3+Q6 -> 3.5 | S3: =Q13 -> 5 | T3: =S3+1&"-"&U3 -> 6-6 | U3: =S3+U6 -> 6 | W3: =U3 -> 6 | X3: =W3+1&"-"&Y3 -> 7-7,5 | Y3: =W3+Y6 -> 7.5 | AA3: =Y8 -> 8 | AB3: =AA3+1&"-"&AC3 -> 9-9,5 | AC3: =AA3+AC6 -> 9.5
B4: e se factível, a redução em até 5,5 dias, independentemente do custo. | K4: A | O4: B | S4: F | W4: G | AA4: I
B6: Pede-se: | K6: 1 | L6: =B15&","&B17 -> Version,Cursor | M6: 2.5 | O6: 2 | P6: =B14 -> Select | Q6: 1 | S6: 6 | T6: =B23 -> Order | U6: 1 | W6: 7 | X6: =B16&","&B24 -> Parse,Dbld | Y6: 1.5 | AA6: 9 | AB6: =B14 -> Select | AC6: 1.5
B7: Apresentar a duração e o custo da melhor segunda versão, bem como descrever
B8: detalhadamente as alterações feitas. | O8: =M3 -> 2.5 | P8: =O8+1&"-"&Q8 -> 3,5-4 | Q8: =O8+Q11 -> 4 | W8: =U3 -> 6 | X8: =W8+1&"-"&Y8 -> 7-8 | Y8: =W8+Y11 -> 8
O9: C | W9: H
B10: Obs.: elaborar na planilha todos os diagramas e cálculos pertinentes.
O11: 3 | P11: =B21&","&B20 -> Where,From | Q11: 1.5 | W11: 8 | X11: =B19&","&B23 -> Choose,Order | Y11: 2
B13: RECURSO | C13: CUSTO/HORA | E13: A duração do Projeto em dias seguidos: | I13: 9,5 dias | O13: =M3 -> 2.5 | P13: =O13+1&"-"&Q13 -> 3,5-5 | Q13: =O13+Q16 -> 5
B14: Select | C14: =640/8 -> 80 | E14: A data do início: | I14: 45975 | O14: D
B15: Version | C15: =75 -> 75 | I15: pela manhã as 08h00
B16: Parse | C16: =40 -> 40 | O16: 4 | P16: =B16&","&B25 -> Parse,UserId | Q16: 2.5
B17: Cursor | C17: =12000/15/8 -> 100 | E17: Tabela
B18: Datetime | C18: =50 -> 50 | E18: Tarefa | F18: RH Alocado | G18: Custo T RH | H18: Outros Custos | I18: Custo da Tarefa | O18: =M3 -> 2.5 | P18: =O18+1&"-"&Q18 -> 3,5-4,5 | Q18: =O18+Q21 -> 4.5
B19: Choose | C19: =8400/30/8 -> 35 | E19: 1 | F19: =L6 -> Version,Cursor | G19: =(C15*M6*8)+(C17*M6*8) -> 3500 | H19: 1000 | I19: =G19+H19 -> 4500 | O19: E
B20: From | C20: =480/8 -> 60 | E20: 2 | F20: =P6 -> Select | G20: =C14*Q6*8 -> 640 | H20: 0 | I20: =G20+H20 -> 640
B21: Where | C21: =30 -> 30 | E21: 3 | F21: =P11 -> Where,From | G21: =(C21*Q11*8)+(C20*Q11*8) -> 1080 | H21: 0 | I21: =G21+H21 -> 1080 | O21: 5 | P21: =B19&","&B22 -> Choose,Use | Q21: 2
B22: Use | C22: =85 -> 85 | E22: 4 | F22: =P16 -> Parse,UserId | G22: =(C16*Q16*8)+(C25*Q16*8) -> 1300 | H22: 2500 | I22: =G22+H22 -> 3800
B23: Order | C23: =6720/7/8 -> 120 | E23: 5 | F23: =P21 -> Choose,Use | G23: =(C19*Q21*8)+(C22*Q21*8) -> 1920 | H23: 650 | I23: =G23+H23 -> 2570
B24: Dbld | C24: =100 -> 100 | E24: 6 | F24: =T6 -> Order | G24: =C23*U6*8 -> 960 | H24: 1780 | I24: =G24+H24 -> 2740 | O24: Eu aloquei 2 recursos nas tarefas 1;3;4;5;7;8 redezuindo assim pela metade a duração das mesmas tarefas,
B25: UserId | C25: =200/8 -> 25 | E25: 7 | F25: =X6 -> Parse,Dbld | G25: =(C16*Y6*8)+(C24*Y6*8) -> 1680 | H25: 0 | I25: =G25+H25 -> 1680 | O25: por exemplo, uma tarefa que durava 4 dias para ser concluida, começa agora a durar 2 dias com duas pessoas realizando a mesma
E26: 8 | F26: =X11 -> Choose,Order | G26: =(C19*Y11*8)+(C23*Y11*8) -> 2480 | H26: 3000 | I26: =G26+H26 -> 5480
E27: 9 | F27: =AB6 -> Select | G27: =(C14*AC6*8) -> 960 | H27: 1500 | I27: =G27+H27 -> 2460
E28: Total | I28: =SUM(I19:I27) -> 24950
